{
    "crg": {
        "change_language": "ಭಾಷೆ ಬದಲಾಯಿಸಿ",
        "change_language_alert": "ನಿಮ್ಮ ಅಪ್ಲಿಕೇಶನ್ ಭಾಷೆಯನ್ನು ಬದಲಾಯಿಸಿ, ಯಾವುದಾದರೂ ಒಂದನ್ನು ಆರಿಸಿ!",
        "english_lang": "ಆಂಗ್ಲ",
        "coorg_language": "ಕರ್ನಾಟಕ",
        "language_setting": "ಭಾಷೆಯ ಸೆಟ್ಟಿಂಗ್‌ಗಳು",
        "edit_profile": "ಪ್ರೊಫೈಲ್ ಬದಲಿಸು",
        "reward_offer": "ಬಹುಮಾನ ಮತ್ತು ಕೊಡುಗೆಗಳು",
        "transaction_history": "ವಹಿವಾಟಿನ ಇತಿಹಾಸ",
        "booking_history": "ಬುಕಿಂಗ್ ಇತಿಹಾಸ",
        "settings": "ಸಂಯೋಜನೆಗಳು",
        "privacy_policy": "ಗೌಪ್ಯತಾ ನೀತಿ",
        "term_sconditions": "ನಿಯಮ ಮತ್ತು ಶರತ್ತುಗಳು",
        "log_out": "ಲಾಗ್ ಔಟ್",
        "'logged_out'": "ಲಾಗ್ ಔಟ್",
        "logged_out_alert": "ನೀವು ಖಚಿತವಾಗಿ, ಲಾಗ್ ಔಟ್ ಮಾಡಲು ಬಯಸುವಿರಾ?",
        "yes": "ಹೌದು",
        "no": "ಸಂ",
        "feels_like": "ಭಾಸವಾಗುತ್ತಿದೆ",
        "where_are_you_going": "ನೀವು ಎಲ್ಲಿಗೆ ಹೋಗುತ್ತಿದ್ದೀರಾ?",
        "your_last_trip": "ನಿಮ್ಮ ಕೊನೆಯ ಪ್ರವಾಸ",
        "view_all": "ಎಲ್ಲಾ ವೀಕ್ಷಿಸಿ",
        "no_trip_nound": "ಯಾವುದೇ ಪ್ರವಾಸ ಕಂಡುಬಂದಿಲ್ಲ",
        "auto": "ಆಟೋ",
        "phramacy": "ಔಷಧಾಲಯ",
        "hotel": "ಹೋಟೆಲ್",
        "market": "ಮಾರುಕಟ್ಟೆ",
        "food": "ಆಹಾರ",
        "profile": "ಪ್ರೊಫೈಲ್",
        "search_destination": "ಗಮ್ಯಸ್ಥಾನವನ್ನು ಹುಡುಕಿ",
        "enter_drop_location": "ಡ್ರಾಪ್ ಸ್ಥಳವನ್ನು ನಮೂದಿಸಿ",
        "create_ride": "ರೈಡ್ ರಚಿಸಿ",
        "booking_details": "ಬುಕಿಂಗ್ ವಿವರಗಳು",
        "apply_coupon_code": "ಕೂಪನ್ ಕೋಡ್ ಅನ್ನು ಅನ್ವಯಿಸಿ",
        "book_auto": "ನಿಮ್ಮ ಆಟೋವನ್ನು ದೃಢೀಕರಿಸಿ", 
        "waiting_time": "ಕಾಯುವ ಸಮಯ",
        "waiting_for_driver": "ಚಾಲಕನಿಗಾಗಿ ಕಾಯಲಾಗುತ್ತಿದೆ",
        "fare_price_information": "ದರದ ಮಾಹಿತಿ",
        "total_estimated_fare_price_including_taxes": "ತೆರಿಗೆಗಳನ್ನು ಒಳಗೊಂಡಂತೆ ಒಟ್ಟು ಅಂದಾಜು ದರದ ಬೆಲೆ.",
        "price_may_toll_area": "ದರ ಒಳಗೊಂಡಿದೆ : 2 ಕಿಮೀ ವರೆಗೆ ಕನಿಷ್ಠ ದರ ರೂ.40 | ಪ್ರತಿ ಕಿಮೀ ದರ - ರೂ.20 |",
        "cost_details": "ರಾತ್ರಿಯ ಸಮಯದ ಶುಲ್ಕಗಳು 1.5x ರಾತ್ರಿ 10 ರಿಂದ ಬೆಳಿಗ್ಗೆ 5 ರವರೆಗೆ ಅನ್ವಯಿಸುತ್ತದೆ.",
        "ride_fare": "ಸವಾರಿ ದರ",
        "cost_details_part": ", ಪ್ರಯಾಣ ದರದ ಮೇಲೆ 5% GST",
        "cost_details_part_one": ", & ಮತ್ತು 7.90/km ಪೋಸ್ಟ್ 12 KMs",
        "got_it": "ಅರ್ಥವಾಯಿತು",
        "payment_method": "ಪಾವತಿ ವಿಧಾನ",
        "choose_your_payment_options": "ನಿಮ್ಮ ಪಾವತಿ ಆಯ್ಕೆಗಳನ್ನು ಆರಿಸಿ",
        "wallet": "ವಾಲೆಟ್",
        "cash": "ನಗದು",
        "end_trip": "ಪ್ರವಾಸವನ್ನು ಕೊನೆಗೊಳಿಸಿ",
        "end_trip_now": "ನೀವು ಈ ಪ್ರವಾಸವನ್ನು ಕೊನೆಗೊಳಿಸಲು ಬಯಸುವಿರಾ?",
        "loggout_successfull": "ಲಾಗ್‌ಔಟ್ ಯಶಸ್ವಿಯಾಗಿದೆ!",
        "congratulations_loggout_successfully": "ಅಭಿನಂದನೆಗಳು, ಲಾಗ್‌ಔಟ್ ಯಶಸ್ವಿಯಾಗಿ!",
        "duty_on": "ಡ್ಯೂಟಿ ಆನ್",
        "duty_off": "ಡ್ಯೂಟಿ ಆಫ್",
        "driver_logged_out": "ಚಾಲಕ ಲಾಗ್‌ಔಟ್",
        "earning_history": "ಗಳಿಕೆಯ ಇತಿಹಾಸ",
        "vehicle_details": "ವಾಹನದ ವಿವರಗಳು",
        "total_balance": "ಒಟ್ಟು ಬ್ಯಾಲೆನ್ಸ್",
        "details_balance": "ವಿವರಗಳು ಬ್ಯಾಲೆನ್ಸ್",
        "upcoming_trip_request": "ಮುಂಬರುವ ಪ್ರವಾಸದ ವಿನಂತಿ",
        "search_trips": "ಪ್ರವಾಸಗಳನ್ನು ಹುಡುಕಿ...",
        "mobile": "ಮೊಬೈಲ್",
        "enter_digit_mobile_number": "10 ಅಂಕಿಗಳ ಮೊಬೈಲ್ ಸಂಖ್ಯೆಯನ್ನು ನಮೂದಿಸಿ",
        "button_you_agree_with_the": "ಬಟನ್ ಅನ್ನು ಕ್ಲಿಕ್ ಮಾಡುವ ಮೂಲಕ ನೀವು ಒಪ್ಪುತ್ತೀರಿ",
        "terms_&_conditions_and_privacy_policy": "ನಿಯಮಗಳು ಮತ್ತು ಷರತ್ತುಗಳು ಮತ್ತು ಗೌಪ್ಯತೆ ನೀತಿ",
        "send_OTP": "OTP ಕಳುಹಿಸಿ",
        "partner_with_us": "ನಮ್ಮೊಂದಿಗೆ ಪಾಲುದಾರ",
        "no_upcoming_trip": "ಮುಂಬರುವ ಪ್ರವಾಸವಿಲ್ಲ",
        "rate_your_driver": "ನಿಮ್ಮ ಚಾಲಕವನ್ನು ರೇಟ್ ಮಾಡಿ",
        "rate_your_driver_info": "ಚಾಲನಾ ಕೌಶಲ್ಯ ಮತ್ತು ನಡವಳಿಕೆಗಾಗಿ ನಿಮ್ಮ ಚಾಲಕನನ್ನು ರೇಟ್ ಮಾಡಿ ಮತ್ತು ನೀವು ಯಾವುದೇ ಸಲಹೆಯನ್ನು ಹೊಂದಿದ್ದೀರಾ ದಯವಿಟ್ಟು ಬರೆಯಿರಿ.",
        "please_write_your_feedback": "ದಯವಿಟ್ಟು ನಿಮ್ಮ ಪ್ರತಿಕ್ರಿಯೆಯನ್ನು ಬರೆಯಿರಿ",
        "submit":"ಸಲ್ಲಿಸು",
        "final_ride_cost":"ಒಟ್ಟು ದರ",
        "tax_or_charges":"ತೆರಿಗೆ ಮತ್ತು ಇತರೆ ಶುಲ್ಕಗಳು"
    }
}